createdb/__init__.py
createdb/admin.py
createdb/apps.py
createdb/models.py
createdb/py.typed
createdb/tests.py
createdb/views.py
createdb/management/__init__.py
createdb/management/commands/__init__.py
createdb/management/commands/_lib.py
createdb/management/commands/createdb.py
createdb/migrations/__init__.py
django_createdb/__init__.py
django_createdb/asgi.py
django_createdb/settings.py
django_createdb/urls.py
django_createdb/wsgi.py
django_createdb-0.2.0.dist-info/LICENSE
django_createdb-0.2.0.dist-info/METADATA
django_createdb-0.2.0.dist-info/WHEEL
django_createdb-0.2.0.dist-info/top_level.txt
django_createdb-0.2.0.dist-info/RECORD
