Metadata-Version: 2.1
Name: django-createdb
Version: 0.2.0
Summary: A django extension for creating sqlite3, postgresql based on settings.py
Home-page: https://github.com/The-Flash/django_createdb
Author: Augustine Smith
Author-email: absaugustineflash@gmail.com
License: MIT
Platform: UNKNOWN
Classifier: Environment :: Web Environment
Classifier: Framework :: Django
Classifier: Intended Audience :: Developers
Classifier: License :: OSI Approved :: MIT License
Classifier: Operating System :: OS Independent
Classifier: Programming Language :: Python
Classifier: Programming Language :: Python :: 3
Classifier: Programming Language :: Python :: 3 :: Only
Classifier: Programming Language :: Python :: 3.8
Classifier: Programming Language :: Python :: 3.9
Requires-Python: >=3.8
Requires-Dist: Django (>=3.2)
